.coveragerc
.pylintrc
.travis.yml
AUTHORS
ChangeLog
LICENSE
MANIFEST.in
Makefile
README.md
requirements.txt
setup.cfg
setup.py
tox.ini
doc/api.rst
doc/changelog.rst
doc/conf.py
doc/index.rst
doc/user_guide.rst
doc/user_guide.rst.ctx.py
doc/_static/pact-logo.png
pact/__init__.py
pact/_compat.py
pact/base.py
pact/group.py
pact/pact.py
pact/utils.py
pact.egg-info/PKG-INFO
pact.egg-info/SOURCES.txt
pact.egg-info/dependency_links.txt
pact.egg-info/not-zip-safe
pact.egg-info/pbr.json
pact.egg-info/requires.txt
pact.egg-info/top_level.txt
tests/__init__.py
tests/conftest.py
tests/doctest_utils.py
tests/test_doctests.py
tests/test_pact.py
tests/test_pact_group.py