Metadata-Version: 2.1
Name: pact
Version: 1.12.0
Summary: Promises library in Python
Home-page: https://github.com/getslash/pact
Author: Rotem Yaari
Author-email: vmalloc@gmail.com
License: BSD3
Platform: UNKNOWN
Classifier: Programming Language :: Python :: 2.7
Classifier: Programming Language :: Python :: 3.4
Classifier: Programming Language :: Python :: 3.5
Classifier: Programming Language :: Python :: 3.6
Classifier: Programming Language :: Python :: 3.7
Provides-Extra: testing
Provides-Extra: doc
